mlcookiecutter/__init__.py
mlcookiecutter/main.py
mlcookiecutter-1.1.0.dist-info/METADATA
mlcookiecutter-1.1.0.dist-info/WHEEL
mlcookiecutter-1.1.0.dist-info/entry_points.txt
mlcookiecutter-1.1.0.dist-info/top_level.txt
mlcookiecutter-1.1.0.dist-info/RECORD
