Metadata-Version: 2.1
Name: mlcookiecutter
Version: 1.1.0
Summary: A tool to create project structures for ml/data
Home-page: https://github.com/sarag5/mlcookiecutter
Author: sarag5
Author-email: sabarinathan_96@proton.me
Classifier: Programming Language :: Python :: 3
Classifier: License :: OSI Approved :: MIT License
Classifier: Operating System :: OS Independent
Requires-Python: >=3.6
Requires-Dist: click
Requires-Dist: requests
